rb/__init__.py
rb/_rediscommands.py
rb/clients.py
rb/cluster.py
rb/ketama.py
rb/poll.py
rb/promise.py
rb/router.py
rb/testing.py
rb/utils.py
rb-1.10.0.dist-info/LICENSE
rb-1.10.0.dist-info/METADATA
rb-1.10.0.dist-info/WHEEL
rb-1.10.0.dist-info/top_level.txt
rb-1.10.0.dist-info/RECORD
