Metadata-Version: 2.1
Name: rb
Version: 1.10.0
Summary: rb, the redis blaster
Home-page: http://github.com/getsentry/rb
Author: Functional Software Inc.
Author-email: hello@getsentry.com
License: UNKNOWN
Platform: UNKNOWN
Classifier: License :: OSI Approved :: Apache Software License
Classifier: Programming Language :: Python
Requires-Dist: redis (!=3.4.0,>=2.6)
